core/__init__.py
core/cli.py
core/enhancer.py
core/exts_map.py
core/highlight_lexer.py
core/i18n.py
core/log.py
core/name_resolver.py
core/question.py
core/solution.py
core/transport.py
core/utils.py
main/__init__.py
lee-1.4.0.dist-info/METADATA
lee-1.4.0.dist-info/WHEEL
lee-1.4.0.dist-info/entry_points.txt
lee-1.4.0.dist-info/top_level.txt
lee-1.4.0.dist-info/RECORD
