Metadata-Version: 2.1
Name: lee
Version: 1.4.0
Summary: yet another leetcode cli command
Home-page: https://github.com/zk4/lee
Author: zk
Author-email: liuzq7@gmail.com
License: UNKNOWN
Project-URL: Bug Reports, https://github.com/zk4/lee/issues
Project-URL: Funding, https://donate.pypi.org
Project-URL: Say Thanks!, http://saythanks.io/to/example
Project-URL: Source, https://github.com/zk4/lee/
Keywords: leetcode cli
Platform: UNKNOWN
Classifier: Development Status :: 3 - Alpha
Classifier: Intended Audience :: Developers
Classifier: Topic :: Software Development :: Build Tools
Classifier: License :: OSI Approved :: MIT License
Classifier: Programming Language :: Python :: 3
Classifier: Programming Language :: Python :: 3.5
Classifier: Programming Language :: Python :: 3.6
Classifier: Programming Language :: Python :: 3.7
Requires-Python: >=3.0
Requires-Dist: diskcache
Requires-Dist: beautifulsoup4
Requires-Dist: html2markdown
Requires-Dist: requests
Requires-Dist: termcolor
Requires-Dist: Pygments
Requires-Dist: halo
Provides-Extra: dev
Requires-Dist: check-manifest ; extra == 'dev'
Provides-Extra: test
Requires-Dist: coverage ; extra == 'test'
